bucketlist_api/__init__.py
bucketlist_api/main.py
bucketlist_api/models.py
bucketlist_api-1.0.dist-info/DESCRIPTION.rst
bucketlist_api-1.0.dist-info/METADATA
bucketlist_api-1.0.dist-info/RECORD
bucketlist_api-1.0.dist-info/WHEEL
bucketlist_api-1.0.dist-info/metadata.json
bucketlist_api-1.0.dist-info/top_level.txt
