Metadata-Version: 2.0
Name: bucketlist-api
Version: 1.0
Summary: A RESTful api for an online bucketlist service
Home-page: https://github.com/giddygitau/bucketlist
Author: Gideon Gitau
Author-email: nggitau@gmail.com
License: MIT
Download-URL: https://github.com/giddygitau/bucketlist/archive/1.0.tar.gz
Platform: UNKNOWN
Requires-Dist: faker
Requires-Dist: flask
Requires-Dist: flask-bcrypt
Requires-Dist: flask-jwt
Requires-Dist: flask-migrate
Requires-Dist: flask-restful
Requires-Dist: flask-script
Requires-Dist: flask-sqlalchemy
